{
  "project_info": {
    "project_number": "428099524677",
    "firebase_url": "https://rs-jakarta-mobile.firebaseio.com",
    "project_id": "rs-jakarta-mobile",
    "storage_bucket": "rs-jakarta-mobile.appspot.com"
  },
  "client": [
    {
      "client_info": {
        "mobilesdk_app_id": "1:428099524677:android:44faa13cd45e1e47f5ab2c",
        "android_client_info": {
          "package_name": "com.wamplo.rs_jakarta_mobile"
        }
      },
      "oauth_client": [
        {
          "client_id": "428099524677-2frg5qi1a0lair28c6rd1jta5f07j9b6.apps.googleusercontent.com",
          "client_type": 3
        }
      ],
      "api_key": [
        {
          "current_key": "AIzaSyCmWulDINylC_7KR1aSRxaOPe6mzMfpgO4"
        }
      ],
      "services": {
        "appinvite_service": {
          "other_platform_oauth_client": [
            {
              "client_id": "428099524677-2frg5qi1a0lair28c6rd1jta5f07j9b6.apps.googleusercontent.com",
              "client_type": 3
            }
          ]
        }
      }
    }
  ],
  "configuration_version": "1"
}